python_copier_template_example/__init__.py
python_copier_template_example/__main__.py
python_copier_template_example/_version.py
dls_python_copier_template_example-0.5.4.dist-info/LICENSE
dls_python_copier_template_example-0.5.4.dist-info/METADATA
dls_python_copier_template_example-0.5.4.dist-info/WHEEL
dls_python_copier_template_example-0.5.4.dist-info/entry_points.txt
dls_python_copier_template_example-0.5.4.dist-info/top_level.txt
dls_python_copier_template_example-0.5.4.dist-info/RECORD
